[
  {
    "full_name": "aviyelverse/Open-Source-Requests",
    "stargazers_count": 18,
    "open_issues_count": 113,
    "forks_count": 4
  },
  {
    "full_name": "calcom/cal.com",
    "stargazers_count": 29113,
    "open_issues_count": 771,
    "forks_count": 6676
  },
  {
    "full_name": "carbon-language/carbon-lang",
    "stargazers_count": 32282,
    "open_issues_count": 118,
    "forks_count": 1468
  },
  {
    "full_name": "freeCodeCamp/mobile",
    "stargazers_count": 411,
    "open_issues_count": 22,
    "forks_count": 121
  },
  {
    "full_name": "tailwindlabs/tailwindcss",
    "stargazers_count": 79036,
    "open_issues_count": 53,
    "forks_count": 3968
  }
]