[
  {
    "full_name": "nhooyr/websocket",
    "stargazers_count": 2948,
    "open_issues_count": 49,
    "forks_count": 231
  },
  {
    "full_name": "Significant-Gravitas/Auto-GPT",
    "stargazers_count": 130970,
    "open_issues_count": 799,
    "forks_count": 26615
  },
  {
    "full_name": "twitter/the-algorithm",
    "stargazers_count": 56901,
    "open_issues_count": 331,
    "forks_count": 11732
  },
  {
    "full_name": "zerodha/gchatgpt",
    "stargazers_count": 74,
    "open_issues_count": 0,
    "forks_count": 9
  },
  {
    "full_name": "github/vscode-github-actions",
    "stargazers_count": 310,
    "open_issues_count": 48,
    "forks_count": 27
  },
  {
    "full_name": "AxiomeCG/awesome-threejs",
    "stargazers_count": 406,
    "open_issues_count": 1,
    "forks_count": 23
  },
  {
    "full_name": "excalidraw/excalidraw",
    "stargazers_count": 48126,
    "open_issues_count": 1035,
    "forks_count": 4084
  },
  {
    "full_name": "ant-design/ant-design",
    "stargazers_count": 85859,
    "open_issues_count": 1000,
    "forks_count": 39528
  },
  {
    "full_name": "atlassian/react-beautiful-dnd",
    "stargazers_count": 29953,
    "open_issues_count": 580,
    "forks_count": 2402
  },
  {
    "full_name": "zenoamaro/react-quill",
    "stargazers_count": 5845,
    "open_issues_count": 307,
    "forks_count": 833
  },
  {
    "full_name": "uber/react-vis",
    "stargazers_count": 8484,
    "open_issues_count": 339,
    "forks_count": 860
  },
  {
    "full_name": "google/styleguide",
    "stargazers_count": 34619,
    "open_issues_count": 316,
    "forks_count": 13295
  },
  {
    "full_name": "gin-gonic/gin",
    "stargazers_count": 68663,
    "open_issues_count": 689,
    "forks_count": 7439
  },
  {
    "full_name": "fffaraz/awesome-selfhosted-aws",
    "stargazers_count": 172,
    "open_issues_count": 0,
    "forks_count": 12
  },
  {
    "full_name": "github/roadmap",
    "stargazers_count": 7328,
    "open_issues_count": 145,
    "forks_count": 1017
  },
  {
    "full_name": "go-gorm/gorm",
    "stargazers_count": 32382,
    "open_issues_count": 214,
    "forks_count": 3570
  },
  {
    "full_name": "gofiber/fiber",
    "stargazers_count": 26250,
    "open_issues_count": 45,
    "forks_count": 1313
  },
  {
    "full_name": "calibreapp/image-actions",
    "stargazers_count": 1301,
    "open_issues_count": 22,
    "forks_count": 70
  },
  {
    "full_name": "styled-components/styled-components",
    "stargazers_count": 38857,
    "open_issues_count": 165,
    "forks_count": 2446
  },
  {
    "full_name": "Atarity/deploy-your-own-saas",
    "stargazers_count": 4303,
    "open_issues_count": 1,
    "forks_count": 264
  },
  {
    "full_name": "tiimgreen/github-cheat-sheet",
    "stargazers_count": 40919,
    "open_issues_count": 29,
    "forks_count": 5279
  },
  {
    "full_name": "privatenumber/snap-tweet",
    "stargazers_count": 312,
    "open_issues_count": 6,
    "forks_count": 17
  },
  {
    "full_name": "szabgab/awesome-for-non-programmers",
    "stargazers_count": 792,
    "open_issues_count": 1,
    "forks_count": 133
  },
  {
    "full_name": "golang/go",
    "stargazers_count": 111299,
    "open_issues_count": 8328,
    "forks_count": 16513
  },
  {
    "full_name": "avelino/awesome-go",
    "stargazers_count": 101463,
    "open_issues_count": 140,
    "forks_count": 10943
  },
  {
    "full_name": "sdras/awesome-actions",
    "stargazers_count": 21458,
    "open_issues_count": 105,
    "forks_count": 1376
  },
  {
    "full_name": "devrelcollective/awesome-devrel",
    "stargazers_count": 600,
    "open_issues_count": 7,
    "forks_count": 89
  },
  {
    "full_name": "dailydotdev/daily",
    "stargazers_count": 12760,
    "open_issues_count": 40,
    "forks_count": 390
  },
  {
    "full_name": "unskript/Awesome-CloudOps-Automation",
    "stargazers_count": 152,
    "open_issues_count": 123,
    "forks_count": 23
  },
  {
    "full_name": "lemokami/startupsofkerala",
    "stargazers_count": 21,
    "open_issues_count": 1,
    "forks_count": 16
  }
]